{
	"completely_empty": false,
	"image": {
		"height": 860,
		"scale": 1.1616279069767441,
		"width": 645
	},
	"mark": [
		{
			"class_idx": 0,
			"name": "lisenceplate",
			"points": [
				{
					"int_x": 513,
					"int_y": 354,
					"x": 0.7953488371999999,
					"y": 0.411627907
				},
				{
					"int_x": 565,
					"int_y": 354,
					"x": 0.8759689922,
					"y": 0.411627907
				},
				{
					"int_x": 565,
					"int_y": 508,
					"x": 0.8759689922,
					"y": 0.5906976744
				},
				{
					"int_x": 513,
					"int_y": 508,
					"x": 0.7953488371999999,
					"y": 0.5906976744
				}
			],
			"rect": {
				"h": 0.17906976739999997,
				"int_h": 155,
				"int_w": 53,
				"int_x": 513,
				"int_y": 354,
				"w": 0.08062015500000008,
				"x": 0.7953488371999999,
				"y": 0.411627907
			}
		}
	],
	"timestamp": 1738632570,
	"version": "1.10.18-1"
}
