{
	"completely_empty": false,
	"image": {
		"height": 600,
		"scale": 1.665,
		"width": 800
	},
	"mark": [
		{
			"class_idx": 0,
			"name": "lisenceplate",
			"points": [
				{
					"int_x": 305,
					"int_y": 90,
					"x": 0.38125,
					"y": 0.14999999995000002
				},
				{
					"int_x": 361,
					"int_y": 90,
					"x": 0.45125000000000004,
					"y": 0.14999999995000002
				},
				{
					"int_x": 361,
					"int_y": 199,
					"x": 0.45125000000000004,
					"y": 0.33166666665
				},
				{
					"int_x": 305,
					"int_y": 199,
					"x": 0.38125,
					"y": 0.33166666665
				}
			],
			"rect": {
				"h": 0.18166666669999998,
				"int_h": 110,
				"int_w": 57,
				"int_x": 305,
				"int_y": 90,
				"w": 0.07000000000000006,
				"x": 0.38125,
				"y": 0.14999999995000002
			}
		}
	],
	"timestamp": 1738632571,
	"version": "1.10.18-1"
}
