{
	"completely_empty": false,
	"image": {
		"height": 800,
		"scale": 1.24875,
		"width": 600
	},
	"mark": [
		{
			"class_idx": 0,
			"name": "lisenceplate",
			"points": [
				{
					"int_x": 326,
					"int_y": 317,
					"x": 0.5433333333,
					"y": 0.39625000000000005
				},
				{
					"int_x": 377,
					"int_y": 317,
					"x": 0.6283333333,
					"y": 0.39625000000000005
				},
				{
					"int_x": 377,
					"int_y": 489,
					"x": 0.6283333333,
					"y": 0.6112500000000001
				},
				{
					"int_x": 326,
					"int_y": 489,
					"x": 0.5433333333,
					"y": 0.6112500000000001
				}
			],
			"rect": {
				"h": 0.21500000000000002,
				"int_h": 173,
				"int_w": 52,
				"int_x": 326,
				"int_y": 317,
				"w": 0.08499999999999996,
				"x": 0.5433333333,
				"y": 0.39625000000000005
			}
		}
	],
	"timestamp": 1738632572,
	"version": "1.10.18-1"
}
