{
	"completely_empty": false,
	"image": {
		"height": 780,
		"scale": 1.2807692307692307,
		"width": 585
	},
	"mark": [
		{
			"class_idx": 0,
			"name": "lisenceplate",
			"points": [
				{
					"int_x": 240,
					"int_y": 313,
					"x": 0.4111111111,
					"y": 0.4008974359
				},
				{
					"int_x": 280,
					"int_y": 313,
					"x": 0.47914529910000003,
					"y": 0.4008974359
				},
				{
					"int_x": 280,
					"int_y": 440,
					"x": 0.47914529910000003,
					"y": 0.5647435896999999
				},
				{
					"int_x": 240,
					"int_y": 440,
					"x": 0.4111111111,
					"y": 0.5647435896999999
				}
			],
			"rect": {
				"h": 0.16384615379999995,
				"int_h": 128,
				"int_w": 41,
				"int_x": 240,
				"int_y": 313,
				"w": 0.06803418800000005,
				"x": 0.4111111111,
				"y": 0.4008974359
			}
		}
	],
	"timestamp": 1738632573,
	"version": "1.10.18-1"
}
