{
	"completely_empty": false,
	"image": {
		"height": 800,
		"scale": 1.24875,
		"width": 600
	},
	"mark": [
		{
			"class_idx": 0,
			"name": "lisenceplate",
			"points": [
				{
					"int_x": 379,
					"int_y": 320,
					"x": 0.632,
					"y": 0.399875
				},
				{
					"int_x": 418,
					"int_y": 320,
					"x": 0.6960000000000001,
					"y": 0.399875
				},
				{
					"int_x": 418,
					"int_y": 431,
					"x": 0.6960000000000001,
					"y": 0.539125
				},
				{
					"int_x": 379,
					"int_y": 431,
					"x": 0.632,
					"y": 0.539125
				}
			],
			"rect": {
				"h": 0.13924999999999998,
				"int_h": 112,
				"int_w": 40,
				"int_x": 379,
				"int_y": 320,
				"w": 0.06400000000000006,
				"x": 0.632,
				"y": 0.399875
			}
		}
	],
	"timestamp": 1738632573,
	"version": "1.10.18-1"
}
