{
	"completely_empty": false,
	"image": {
		"height": 585,
		"scale": 1.7076923076923076,
		"width": 780
	},
	"mark": [
		{
			"class_idx": 0,
			"name": "lisenceplate",
			"points": [
				{
					"int_x": 323,
					"int_y": 86,
					"x": 0.413974359,
					"y": 0.1466666667
				},
				{
					"int_x": 482,
					"int_y": 86,
					"x": 0.6183333334000001,
					"y": 0.1466666667
				},
				{
					"int_x": 482,
					"int_y": 142,
					"x": 0.6183333334000001,
					"y": 0.2430769231
				},
				{
					"int_x": 323,
					"int_y": 142,
					"x": 0.413974359,
					"y": 0.2430769231
				}
			],
			"rect": {
				"h": 0.0964102564,
				"int_h": 57,
				"int_w": 160,
				"int_x": 323,
				"int_y": 86,
				"w": 0.20435897440000006,
				"x": 0.413974359,
				"y": 0.1466666667
			}
		}
	],
	"timestamp": 1738632576,
	"version": "1.10.18-1"
}
