{
	"completely_empty": false,
	"image": {
		"height": 600,
		"scale": 1.665,
		"width": 800
	},
	"mark": [
		{
			"class_idx": 0,
			"name": "lisenceplate",
			"points": [
				{
					"int_x": 430,
					"int_y": 95,
					"x": 0.5375,
					"y": 0.15833333335
				},
				{
					"int_x": 493,
					"int_y": 95,
					"x": 0.6162500000000001,
					"y": 0.15833333335
				},
				{
					"int_x": 493,
					"int_y": 231,
					"x": 0.6162500000000001,
					"y": 0.38500000005
				},
				{
					"int_x": 430,
					"int_y": 231,
					"x": 0.5375,
					"y": 0.38500000005
				}
			],
			"rect": {
				"h": 0.22666666670000002,
				"int_h": 137,
				"int_w": 64,
				"int_x": 430,
				"int_y": 95,
				"w": 0.0787500000000001,
				"x": 0.5375,
				"y": 0.15833333335
			}
		}
	],
	"timestamp": 1738632577,
	"version": "1.10.18-1"
}
