{
	"completely_empty": false,
	"image": {
		"height": 600,
		"scale": 1.665,
		"width": 800
	},
	"mark": [
		{
			"class_idx": 0,
			"name": "lisenceplate",
			"points": [
				{
					"int_x": 340,
					"int_y": 379,
					"x": 0.425375,
					"y": 0.6319999999499999
				},
				{
					"int_x": 405,
					"int_y": 379,
					"x": 0.506625,
					"y": 0.6319999999499999
				},
				{
					"int_x": 405,
					"int_y": 502,
					"x": 0.506625,
					"y": 0.83666666665
				},
				{
					"int_x": 340,
					"int_y": 502,
					"x": 0.425375,
					"y": 0.83666666665
				}
			],
			"rect": {
				"h": 0.2046666667000001,
				"int_h": 124,
				"int_w": 66,
				"int_x": 340,
				"int_y": 379,
				"w": 0.08124999999999999,
				"x": 0.425375,
				"y": 0.6319999999499999
			}
		}
	],
	"timestamp": 1738632578,
	"version": "1.10.18-1"
}
