{
	"completely_empty": false,
	"image": {
		"height": 600,
		"scale": 1.665,
		"width": 800
	},
	"mark": [
		{
			"class_idx": 0,
			"name": "lisenceplate",
			"points": [
				{
					"int_x": 248,
					"int_y": 26,
					"x": 0.309875,
					"y": 0.04416666664999999
				},
				{
					"int_x": 524,
					"int_y": 26,
					"x": 0.654625,
					"y": 0.04416666664999999
				},
				{
					"int_x": 524,
					"int_y": 112,
					"x": 0.654625,
					"y": 0.18649999995
				},
				{
					"int_x": 248,
					"int_y": 112,
					"x": 0.309875,
					"y": 0.18649999995
				}
			],
			"rect": {
				"h": 0.1423333333,
				"int_h": 87,
				"int_w": 277,
				"int_x": 248,
				"int_y": 26,
				"w": 0.34475,
				"x": 0.309875,
				"y": 0.04416666664999999
			}
		}
	],
	"timestamp": 1738682192,
	"version": "1.10.18-1"
}
