{
	"completely_empty": false,
	"image": {
		"height": 600,
		"scale": 1.665,
		"width": 800
	},
	"mark": [
		{
			"class_idx": 0,
			"name": "lisenceplate",
			"points": [
				{
					"int_x": 291,
					"int_y": 212,
					"x": 0.36425,
					"y": 0.3536666667
				},
				{
					"int_x": 359,
					"int_y": 212,
					"x": 0.44825,
					"y": 0.3536666667
				},
				{
					"int_x": 359,
					"int_y": 391,
					"x": 0.44825,
					"y": 0.6516666667000001
				},
				{
					"int_x": 291,
					"int_y": 391,
					"x": 0.36425,
					"y": 0.6516666667000001
				}
			],
			"rect": {
				"h": 0.29800000000000004,
				"int_h": 180,
				"int_w": 69,
				"int_x": 291,
				"int_y": 212,
				"w": 0.08399999999999996,
				"x": 0.36425,
				"y": 0.3536666667
			}
		}
	],
	"timestamp": 1738682193,
	"version": "1.10.18-1"
}
