{
	"completely_empty": false,
	"image": {
		"height": 800,
		"scale": 1.24875,
		"width": 600
	},
	"mark": [
		{
			"class_idx": 0,
			"name": "lisenceplate",
			"points": [
				{
					"int_x": 216,
					"int_y": 438,
					"x": 0.36,
					"y": 0.5475
				},
				{
					"int_x": 372,
					"int_y": 438,
					"x": 0.62,
					"y": 0.5475
				},
				{
					"int_x": 372,
					"int_y": 495,
					"x": 0.62,
					"y": 0.61875
				},
				{
					"int_x": 216,
					"int_y": 495,
					"x": 0.36,
					"y": 0.61875
				}
			],
			"rect": {
				"h": 0.07125000000000004,
				"int_h": 58,
				"int_w": 157,
				"int_x": 216,
				"int_y": 438,
				"w": 0.26,
				"x": 0.36,
				"y": 0.5475
			}
		}
	],
	"timestamp": 1738682152,
	"version": "1.10.18-1"
}
