{
	"completely_empty": false,
	"image": {
		"height": 600,
		"scale": 1.665,
		"width": 800
	},
	"mark": [
		{
			"class_idx": 0,
			"name": "lisenceplate",
			"points": [
				{
					"int_x": 331,
					"int_y": 220,
					"x": 0.41375000000000006,
					"y": 0.36666666665000003
				},
				{
					"int_x": 507,
					"int_y": 220,
					"x": 0.63375,
					"y": 0.36666666665000003
				},
				{
					"int_x": 507,
					"int_y": 288,
					"x": 0.63375,
					"y": 0.47999999995
				},
				{
					"int_x": 331,
					"int_y": 288,
					"x": 0.41375000000000006,
					"y": 0.47999999995
				}
			],
			"rect": {
				"h": 0.11333333329999995,
				"int_h": 69,
				"int_w": 177,
				"int_x": 331,
				"int_y": 220,
				"w": 0.21999999999999997,
				"x": 0.41375000000000006,
				"y": 0.36666666665000003
			}
		}
	],
	"timestamp": 1738682195,
	"version": "1.10.18-1"
}
