{
	"completely_empty": false,
	"image": {
		"height": 385,
		"scale": 2.5083333333333333,
		"width": 720
	},
	"mark": [
		{
			"class_idx": 0,
			"name": "lisenceplate",
			"points": [
				{
					"int_x": 270,
					"int_y": 207,
					"x": 0.3745567375886525,
					"y": 0.53646408839779
				},
				{
					"int_x": 317,
					"int_y": 207,
					"x": 0.4404550827423168,
					"y": 0.53646408839779
				},
				{
					"int_x": 317,
					"int_y": 228,
					"x": 0.4404550827423168,
					"y": 0.5928176795580111
				},
				{
					"int_x": 270,
					"int_y": 228,
					"x": 0.3745567375886525,
					"y": 0.5928176795580111
				}
			],
			"rect": {
				"h": 0.056353591160221095,
				"int_h": 22,
				"int_w": 48,
				"int_x": 270,
				"int_y": 207,
				"w": 0.06589834515366433,
				"x": 0.3745567375886525,
				"y": 0.53646408839779
			}
		}
	],
	"timestamp": 1738682103,
	"version": "1.10.18-1"
}
