{
	"completely_empty": false,
	"image": {
		"height": 780,
		"scale": 1.2653846153846153,
		"width": 585
	},
	"mark": [
		{
			"class_idx": 0,
			"name": "lisenceplate",
			"points": [
				{
					"int_x": 428,
					"int_y": 303,
					"x": 0.7307692308,
					"y": 0.38858974360000004
				},
				{
					"int_x": 466,
					"int_y": 303,
					"x": 0.7967521367999999,
					"y": 0.38858974360000004
				},
				{
					"int_x": 466,
					"int_y": 441,
					"x": 0.7967521367999999,
					"y": 0.5647435898000001
				},
				{
					"int_x": 428,
					"int_y": 441,
					"x": 0.7307692308,
					"y": 0.5647435898000001
				}
			],
			"rect": {
				"h": 0.17615384620000002,
				"int_h": 139,
				"int_w": 39,
				"int_x": 428,
				"int_y": 303,
				"w": 0.0659829059999999,
				"x": 0.7307692308,
				"y": 0.38858974360000004
			}
		}
	],
	"timestamp": 1738603285,
	"version": "1.10.18-1"
}
