{
	"completely_empty": false,
	"image": {
		"height": 585,
		"scale": 1.6871794871794872,
		"width": 780
	},
	"mark": [
		{
			"class_idx": 0,
			"name": "lisenceplate",
			"points": [
				{
					"int_x": 520,
					"int_y": 223,
					"x": 0.6662820512500001,
					"y": 0.38102564105000003
				},
				{
					"int_x": 599,
					"int_y": 223,
					"x": 0.76858974355,
					"y": 0.38102564105000003
				},
				{
					"int_x": 599,
					"int_y": 256,
					"x": 0.76858974355,
					"y": 0.43811965815
				},
				{
					"int_x": 520,
					"int_y": 256,
					"x": 0.6662820512500001,
					"y": 0.43811965815
				}
			],
			"rect": {
				"h": 0.05709401709999995,
				"int_h": 34,
				"int_w": 80,
				"int_x": 520,
				"int_y": 223,
				"w": 0.10230769229999992,
				"x": 0.6662820512500001,
				"y": 0.38102564105000003
			}
		}
	],
	"timestamp": 1738603285,
	"version": "1.10.18-1"
}
