{
	"completely_empty": false,
	"image": {
		"height": 780,
		"scale": 1.2653846153846153,
		"width": 602
	},
	"mark": [
		{
			"class_idx": 0,
			"name": "lisenceplate",
			"points": [
				{
					"int_x": 263,
					"int_y": 326,
					"x": 0.4375415282,
					"y": 0.41769230765
				},
				{
					"int_x": 304,
					"int_y": 326,
					"x": 0.5053156146,
					"y": 0.41769230765
				},
				{
					"int_x": 304,
					"int_y": 462,
					"x": 0.5053156146,
					"y": 0.59256410255
				},
				{
					"int_x": 263,
					"int_y": 462,
					"x": 0.4375415282,
					"y": 0.59256410255
				}
			],
			"rect": {
				"h": 0.17487179490000004,
				"int_h": 137,
				"int_w": 42,
				"int_x": 263,
				"int_y": 326,
				"w": 0.06777408639999999,
				"x": 0.4375415282,
				"y": 0.41769230765
			}
		}
	],
	"timestamp": 1738603285,
	"version": "1.10.18-1"
}
