{
	"completely_empty": false,
	"image": {
		"height": 478,
		"scale": 2.064853556485356,
		"width": 719
	},
	"mark": [
		{
			"class_idx": 0,
			"name": "lisenceplate",
			"points": [
				{
					"int_x": 480,
					"int_y": 239,
					"x": 0.6675938804,
					"y": 0.49999999995
				},
				{
					"int_x": 583,
					"int_y": 239,
					"x": 0.8108484006,
					"y": 0.49999999995
				},
				{
					"int_x": 583,
					"int_y": 269,
					"x": 0.8108484006,
					"y": 0.56276150625
				},
				{
					"int_x": 480,
					"int_y": 269,
					"x": 0.6675938804,
					"y": 0.56276150625
				}
			],
			"rect": {
				"h": 0.06276150629999999,
				"int_h": 31,
				"int_w": 104,
				"int_x": 480,
				"int_y": 239,
				"w": 0.14325452019999996,
				"x": 0.6675938804,
				"y": 0.49999999995
			}
		}
	],
	"timestamp": 1738603312,
	"version": "1.10.18-1"
}
