{
	"completely_empty": false,
	"image": {
		"height": 780,
		"scale": 1.2653846153846153,
		"width": 585
	},
	"mark": [
		{
			"class_idx": 0,
			"name": "lisenceplate",
			"points": [
				{
					"int_x": 431,
					"int_y": 616,
					"x": 0.73675213675,
					"y": 0.7897435897
				},
				{
					"int_x": 465,
					"int_y": 616,
					"x": 0.79487179485,
					"y": 0.7897435897
				},
				{
					"int_x": 465,
					"int_y": 689,
					"x": 0.79487179485,
					"y": 0.8833333333
				},
				{
					"int_x": 431,
					"int_y": 689,
					"x": 0.73675213675,
					"y": 0.8833333333
				}
			],
			"rect": {
				"h": 0.09358974359999994,
				"int_h": 74,
				"int_w": 35,
				"int_x": 431,
				"int_y": 616,
				"w": 0.05811965810000008,
				"x": 0.73675213675,
				"y": 0.7897435897
			}
		}
	],
	"timestamp": 1738603313,
	"version": "1.10.18-1"
}
