{
	"completely_empty": false,
	"image": {
		"height": 1600,
		"scale": 0.616875,
		"width": 1167
	},
	"mark": [
		{
			"class_idx": 0,
			"name": "lisenceplate",
			"points": [
				{
					"int_x": 501,
					"int_y": 1033,
					"x": 0.42930591255,
					"y": 0.645625
				},
				{
					"int_x": 559,
					"int_y": 1033,
					"x": 0.47900599824999995,
					"y": 0.645625
				},
				{
					"int_x": 559,
					"int_y": 1187,
					"x": 0.47900599824999995,
					"y": 0.741875
				},
				{
					"int_x": 501,
					"int_y": 1187,
					"x": 0.42930591255,
					"y": 0.741875
				}
			],
			"rect": {
				"h": 0.09624999999999995,
				"int_h": 155,
				"int_w": 59,
				"int_x": 501,
				"int_y": 1033,
				"w": 0.04970008569999995,
				"x": 0.42930591255,
				"y": 0.645625
			}
		}
	],
	"timestamp": 1738603315,
	"version": "1.10.18-1"
}
