{
	"completely_empty": false,
	"image": {
		"height": 720,
		"scale": 1.3708333333333333,
		"width": 720
	},
	"mark": [
		{
			"class_idx": 0,
			"name": "lisenceplate",
			"points": [
				{
					"int_x": 426,
					"int_y": 177,
					"x": 0.5915277778,
					"y": 0.24527777774999998
				},
				{
					"int_x": 551,
					"int_y": 177,
					"x": 0.7645833334,
					"y": 0.24527777774999998
				},
				{
					"int_x": 551,
					"int_y": 229,
					"x": 0.7645833334,
					"y": 0.31861111105
				},
				{
					"int_x": 426,
					"int_y": 229,
					"x": 0.5915277778,
					"y": 0.31861111105
				}
			],
			"rect": {
				"h": 0.07333333330000003,
				"int_h": 53,
				"int_w": 126,
				"int_x": 426,
				"int_y": 177,
				"w": 0.17305555559999997,
				"x": 0.5915277778,
				"y": 0.24527777774999998
			}
		}
	],
	"timestamp": 1738603290,
	"version": "1.10.18-1"
}
