{
	"completely_empty": false,
	"image": {
		"height": 4240,
		"scale": 0.23278301886792452,
		"width": 2400
	},
	"mark": [
		{
			"class_idx": 0,
			"name": "lisenceplate",
			"points": [
				{
					"int_x": 684,
					"int_y": 2022,
					"x": 0.2847916667,
					"y": 0.4769457547
				},
				{
					"int_x": 723,
					"int_y": 2022,
					"x": 0.3010416667,
					"y": 0.4769457547
				},
				{
					"int_x": 723,
					"int_y": 2159,
					"x": 0.3010416667,
					"y": 0.5091391509
				},
				{
					"int_x": 684,
					"int_y": 2159,
					"x": 0.2847916667,
					"y": 0.5091391509
				}
			],
			"rect": {
				"h": 0.032193396199999946,
				"int_h": 138,
				"int_w": 40,
				"int_x": 684,
				"int_y": 2022,
				"w": 0.016249999999999987,
				"x": 0.2847916667,
				"y": 0.4769457547
			}
		},
		{
			"class_idx": 0,
			"name": "lisenceplate",
			"points": [
				{
					"int_x": 682,
					"int_y": 2821,
					"x": 0.2842708333,
					"y": 0.6652712264
				},
				{
					"int_x": 726,
					"int_y": 2821,
					"x": 0.30239583329999997,
					"y": 0.6652712264
				},
				{
					"int_x": 726,
					"int_y": 2960,
					"x": 0.30239583329999997,
					"y": 0.6981721698000001
				},
				{
					"int_x": 682,
					"int_y": 2960,
					"x": 0.2842708333,
					"y": 0.6981721698000001
				}
			],
			"rect": {
				"h": 0.03290094340000005,
				"int_h": 140,
				"int_w": 45,
				"int_x": 682,
				"int_y": 2821,
				"w": 0.018124999999999947,
				"x": 0.2842708333,
				"y": 0.6652712264
			}
		}
	],
	"timestamp": 1738603286,
	"version": "1.10.18-1"
}
