{
	"completely_empty": false,
	"image": {
		"height": 585,
		"scale": 1.6871794871794872,
		"width": 780
	},
	"mark": [
		{
			"class_idx": 0,
			"name": "lisenceplate",
			"points": [
				{
					"int_x": 521,
					"int_y": 221,
					"x": 0.66833333335,
					"y": 0.37811965815000004
				},
				{
					"int_x": 595,
					"int_y": 221,
					"x": 0.76243589745,
					"y": 0.37811965815000004
				},
				{
					"int_x": 595,
					"int_y": 251,
					"x": 0.76243589745,
					"y": 0.42940170945
				},
				{
					"int_x": 521,
					"int_y": 251,
					"x": 0.66833333335,
					"y": 0.42940170945
				}
			],
			"rect": {
				"h": 0.051282051299999964,
				"int_h": 31,
				"int_w": 75,
				"int_x": 521,
				"int_y": 221,
				"w": 0.09410256409999995,
				"x": 0.66833333335,
				"y": 0.37811965815000004
			}
		}
	],
	"timestamp": 1738603290,
	"version": "1.10.18-1"
}
