{
	"completely_empty": false,
	"image": {
		"height": 719,
		"scale": 1.372739916550765,
		"width": 465
	},
	"mark": [
		{
			"class_idx": 0,
			"name": "lisenceplate",
			"points": [
				{
					"int_x": 319,
					"int_y": 83,
					"x": 0.6864516129,
					"y": 0.11557719049999998
				},
				{
					"int_x": 347,
					"int_y": 83,
					"x": 0.7466666666999999,
					"y": 0.11557719049999998
				},
				{
					"int_x": 347,
					"int_y": 148,
					"x": 0.7466666666999999,
					"y": 0.2065368567
				},
				{
					"int_x": 319,
					"int_y": 148,
					"x": 0.6864516129,
					"y": 0.2065368567
				}
			],
			"rect": {
				"h": 0.09095966620000001,
				"int_h": 66,
				"int_w": 29,
				"int_x": 319,
				"int_y": 83,
				"w": 0.06021505379999992,
				"x": 0.6864516129,
				"y": 0.11557719049999998
			}
		}
	],
	"timestamp": 1738603290,
	"version": "1.10.18-1"
}
